Yihui/__init__.py
Yihui/__init__1.py
Yihui/binning.py
Yihui/binning1.py
Yihui/binning_funciton.py
Yihui/cluster.py
Yihui/data_processing.py
Yihui/dataprocessing.py
Yihui/eda.py
Yihui/main.py
Yihui/test.py
Yihui/var_selelct.py
Yihui/yihui.py
Yihuier/__init__.py
Yihuier/__init__1.py
Yihuier/binning.py
Yihuier/binning_funciton.py
Yihuier/cluster.py
Yihuier/data_processing.py
Yihuier/eda.py
Yihuier/main.py
Yihuier/model_evaluation.py
Yihuier/pipeline.py
Yihuier/scorecard_implement.py
Yihuier/scorecard_monitor.py
Yihuier/test.py
Yihuier/third_platform_data_evaluation.py
Yihuier/var_selelct.py
Yihuier/yihui.py
Yihuier/yihuier.py
Yihuier-0.1.13.dist-info/METADATA
Yihuier-0.1.13.dist-info/WHEEL
Yihuier-0.1.13.dist-info/top_level.txt
Yihuier-0.1.13.dist-info/RECORD
