Metadata-Version: 2.1
Name: Yihuier
Version: 0.1.13
Summary: Package for Logistic Regression Modeling, focus on Credit Risk Management
Home-page: https://github.com/encyc/yihuier
Author: encyc
Author-email: atomyuangao@gmail.com
Classifier: Development Status :: 3 - Alpha
Classifier: Programming Language :: Python :: 3.10
Classifier: License :: OSI Approved :: MIT License
Classifier: Operating System :: OS Independent
Classifier: Topic :: Software Development :: Build Tools
Classifier: Intended Audience :: Developers
Requires-Python: >=3.6
Requires-Dist: pandas
Requires-Dist: numpy
Requires-Dist: matplotlib
Requires-Dist: seaborn
Requires-Dist: scikit-learn
Requires-Dist: ydata-profiling ==4.6.3
